cli/__init__.py
cli/cli.py
cli/intro.py
udma/__init__.py
udma/udma.py
udma-1.0b1.dist-info/licenses/LICENSE
udma-1.0b1.dist-info/METADATA
udma-1.0b1.dist-info/WHEEL
udma-1.0b1.dist-info/entry_points.txt
udma-1.0b1.dist-info/top_level.txt
udma-1.0b1.dist-info/RECORD
