Metadata-Version: 2.4
Name: udma
Version: 1.0b1
Summary: Automatic and platform-independent CLI communication system via Ethernet with ComBlock support.
Home-page: https://gitlab.com/ictp-mlab/udma
Author: MLAB-ICTP Team
Author-email: wflorian@ictp.it
License: GPLv3
Classifier: Programming Language :: Python :: 3
Classifier: License :: OSI Approved :: GNU General Public License v3 (GPLv3)
Classifier: Operating System :: OS Independent
Classifier: Development Status :: 4 - Beta
Classifier: Intended Audience :: Developers
Classifier: Topic :: Software Development :: Libraries
Requires-Python: >=3.6
License-File: LICENSE
Requires-Dist: cmd2>=2.4.3
Requires-Dist: appdirs>=1.4.4
Requires-Dist: tqdm>=4.58.0
Dynamic: author
Dynamic: author-email
Dynamic: classifier
Dynamic: description
Dynamic: description-content-type
Dynamic: home-page
Dynamic: license
Dynamic: license-file
Dynamic: requires-dist
Dynamic: requires-python
Dynamic: summary
